todopyedu/__init__.py
todopyedu/__main__.py
todopyedu/cli.py
todopyedu/config.py
todopyedu/database.py
todopyedu/todopyedu.py
todopyedu-1.0.0.dist-info/DESCRIPTION.rst
todopyedu-1.0.0.dist-info/METADATA
todopyedu-1.0.0.dist-info/RECORD
todopyedu-1.0.0.dist-info/WHEEL
todopyedu-1.0.0.dist-info/entry_points.txt
todopyedu-1.0.0.dist-info/metadata.json
todopyedu-1.0.0.dist-info/top_level.txt
