Metadata-Version: 2.0
Name: todopyedu
Version: 1.0.0
Summary: Issue log created for educational purposes
Home-page: https://gitlab.com/kekbek/python-todo
Author: kekbek
Author-email: vadyusha.surin@gmail.com
License: MIT
Platform: UNKNOWN
Classifier: License :: OSI Approved :: MIT License
Classifier: Programming Language :: Python :: 3
Classifier: Programming Language :: Python :: 3.7
Requires-Dist: colorama
Requires-Dist: prettytable
Requires-Dist: shellingham
Requires-Dist: typer
